meggie_statistics/__init__.py
meggie_statistics/configuration.json
meggie_statistics/actions/__init__.py
meggie_statistics/actions/evoked_permutation_test/__init__.py
meggie_statistics/actions/evoked_permutation_test/configuration.json
meggie_statistics/actions/evoked_permutation_test/controller/__init__.py
meggie_statistics/actions/evoked_permutation_test/controller/evoked.py
meggie_statistics/actions/evoked_permutation_test/tests/__init__.py
meggie_statistics/actions/evoked_permutation_test/tests/test_evoked_permutation_test_between_subjects.py
meggie_statistics/actions/evoked_permutation_test/tests/test_evoked_permutation_test_within_subjects.py
meggie_statistics/actions/spectrum_permutation_test/__init__.py
meggie_statistics/actions/spectrum_permutation_test/configuration.json
meggie_statistics/actions/spectrum_permutation_test/controller/__init__.py
meggie_statistics/actions/spectrum_permutation_test/controller/spectrum.py
meggie_statistics/actions/spectrum_permutation_test/tests/__init__.py
meggie_statistics/actions/spectrum_permutation_test/tests/test_spectrum_permutation_test_between_subjects.py
meggie_statistics/actions/spectrum_permutation_test/tests/test_spectrum_permutation_test_within_subjects.py
meggie_statistics/actions/tfr_permutation_test/__init__.py
meggie_statistics/actions/tfr_permutation_test/configuration.json
meggie_statistics/actions/tfr_permutation_test/controller/__init__.py
meggie_statistics/actions/tfr_permutation_test/controller/tfr.py
meggie_statistics/actions/tfr_permutation_test/tests/__init__.py
meggie_statistics/actions/tfr_permutation_test/tests/test_tfr_permutation_test_between_subjects.py
meggie_statistics/actions/tfr_permutation_test/tests/test_tfr_permutation_test_within_subjects.py
meggie_statistics/utilities/__init__.py
meggie_statistics/utilities/stats.py
meggie_statistics/utilities/testing.py
meggie_statistics/utilities/dialogs/__init__.py
meggie_statistics/utilities/dialogs/permutationTestDialogMain.py
meggie_statistics-0.4.0.dist-info/METADATA
meggie_statistics-0.4.0.dist-info/WHEEL
meggie_statistics-0.4.0.dist-info/top_level.txt
meggie_statistics-0.4.0.dist-info/RECORD
